{"ДатаДокумента":"05.11.2022","Продавец":[{"Имя":"Иванов Лев Давидович"},{"Имя":"Петрова Мария Васильевна"}],"Оплата":{"Сумма":"10000,00 рублей","СрокОплаты":"0_1_2_0"},"Покупатель":"ООО Управляющая компания «Арасака»","ПредметДоговора":{"ВидОбъектаНедвижимости":"ЗемельныйУчасток","ВидРазрешенногоИспользования":"для сельскохозяйственного производства","КадастровыйНомер":"1237:09234123532:4521","Площадь":"5 га","Адрес":"Московская область, 5 км от ориентира Ракушки","ОбъектыНаЗемельномУчастке":["здание","склад"],"ОбременениеОбъектаНедвижимости":"ипотека","ОбъектПереданПокупателюДоДоговора":"НЕТ"}}